logging_blueprint/__init__.py
logging_blueprint/conf.py
logging_blueprint/directives.py
logging_blueprint/env.py
logging_blueprint/py.typed
logging_blueprint/styles.py
logging_blueprint/types.py
logging_blueprint/formatter/__init__.py
logging_blueprint/formatter/logfmt.py
logging_blueprint/formatter/pretty.py
logging_blueprint/formatter/utils.py
logging_blueprint-0.0.1.dist-info/METADATA
logging_blueprint-0.0.1.dist-info/WHEEL
logging_blueprint-0.0.1.dist-info/licenses/LICENSE
logging_blueprint-0.0.1.dist-info/RECORD
