Metadata-Version: 2.4
Name: logging-blueprint
Version: 0.0.1
Summary: Environment-driven configuration for Python’s standard library `logging` module.
Project-URL: Repository, https://github.com/eddieland/logging-blueprint
Author-email: Edward Jones <e@eddie.land>
License-Expression: MIT
License-File: LICENSE
Classifier: Development Status :: 2 - Pre-Alpha
Classifier: Intended Audience :: Developers
Classifier: Operating System :: OS Independent
Classifier: Programming Language :: Python
Classifier: Programming Language :: Python :: 3
Classifier: Programming Language :: Python :: 3.10
Classifier: Programming Language :: Python :: 3.11
Classifier: Programming Language :: Python :: 3.12
Classifier: Programming Language :: Python :: 3.13
Classifier: Typing :: Typed
Requires-Python: <4.0,>=3.10
Provides-Extra: json
Requires-Dist: python-json-logger>=3.2.0; extra == 'json'
